kodespel/__init__.py
kodespel/__main__.py
kodespel/kodespel.py
kodespel-0.1.1.data/data/share/kodespel/base.dict
kodespel-0.1.1.data/data/share/kodespel/c.dict
kodespel-0.1.1.data/data/share/kodespel/go.dict
kodespel-0.1.1.data/data/share/kodespel/java.dict
kodespel-0.1.1.data/data/share/kodespel/libc.dict
kodespel-0.1.1.data/data/share/kodespel/python.dict
kodespel-0.1.1.data/data/share/kodespel/unix.dict
kodespel-0.1.1.dist-info/LICENSE.txt
kodespel-0.1.1.dist-info/METADATA
kodespel-0.1.1.dist-info/WHEEL
kodespel-0.1.1.dist-info/entry_points.txt
kodespel-0.1.1.dist-info/top_level.txt
kodespel-0.1.1.dist-info/RECORD
