Metadata-Version: 2.1
Name: kodespel
Version: 0.1.1
Summary: spellchecker for source code
Home-page: https://github.com/gward/kodespel
Author: Greg Ward
Author-email: greg@gerg.ca
License: UNKNOWN
Platform: UNKNOWN
Classifier: Programming Language :: Python :: 3
Classifier: License :: OSI Approved :: BSD License
Classifier: Operating System :: OS Independent
Requires-Python: >=3.6
License-File: LICENSE.txt
